pyconverters_openai_audio/__init__.py
pyconverters_openai_audio/openai_audio.py
pyconverters_openai_audio/openai_utils.py
pyconverters_openai_audio-0.5.45.dist-info/entry_points.txt
pyconverters_openai_audio-0.5.45.dist-info/WHEEL
pyconverters_openai_audio-0.5.45.dist-info/METADATA
pyconverters_openai_audio-0.5.45.dist-info/RECORD
