Metadata-Version: 2.4
Name: pyconverters-openai_audio
Version: 0.5.45
Summary: OpenAIAudio converter
Home-page: https://kairntech.com/
Author: Olivier Terrier
Author-email: olivier.terrier@kairntech.com
Requires-Python: >=3.8
Classifier: Intended Audience :: Information Technology
Classifier: Intended Audience :: System Administrators
Classifier: Operating System :: OS Independent
Classifier: Programming Language :: Python :: 3
Classifier: Programming Language :: Python
Classifier: Topic :: Internet
Classifier: Topic :: Software Development :: Libraries :: Application Frameworks
Classifier: Topic :: Software Development :: Libraries :: Python Modules
Classifier: Topic :: Software Development :: Libraries
Classifier: Topic :: Software Development
Classifier: Typing :: Typed
Classifier: Development Status :: 4 - Beta
Classifier: Environment :: Web Environment
Classifier: Framework :: AsyncIO
Classifier: Intended Audience :: Developers
Classifier: Programming Language :: Python :: 3 :: Only
Classifier: Programming Language :: Python :: 3.8
Classifier: Topic :: Internet :: WWW/HTTP :: HTTP Servers
Classifier: Topic :: Internet :: WWW/HTTP
Requires-Dist: pymultirole-plugins>=0.5.0,<0.6.0
Requires-Dist: openai==1.9.0
Requires-Dist: log-with-context
Requires-Dist: StrEnum
Requires-Dist: filetype==1.0.13
Requires-Dist: requests
Requires-Dist: pydub
Requires-Dist: flit ; extra == "dev"
Requires-Dist: pre-commit ; extra == "dev"
Requires-Dist: bump2version ; extra == "dev"
Requires-Dist: sphinx ; extra == "docs"
Requires-Dist: sphinx-rtd-theme ; extra == "docs"
Requires-Dist: m2r2 ; extra == "docs"
Requires-Dist: sphinxcontrib.apidoc ; extra == "docs"
Requires-Dist: jupyter_sphinx ; extra == "docs"
Requires-Dist: pytest>=7.0 ; extra == "test"
Requires-Dist: pytest-cov ; extra == "test"
Requires-Dist: pytest-flake8 ; extra == "test"
Requires-Dist: pytest-black ; extra == "test"
Requires-Dist: flake8==3.9.2 ; extra == "test"
Requires-Dist: tox ; extra == "test"
Requires-Dist: dirty-equals ; extra == "test"
Requires-Dist: werkzeug==2.0.0 ; extra == "test"
Requires-Dist: flask==2.1.3 ; extra == "test"
Provides-Extra: dev
Provides-Extra: docs
Provides-Extra: test
